LICENSE.txt
MANIFEST.in
README.md
setup.cfg
setup.py
camfi/__init__.py
camfi/_torchutils.py
camfi/_version.py
camfi/annotator.py
camfi/cli.py
camfi/models.py
camfi/projectconfig.py
camfi/transform.py
camfi/util.py
camfi/wingbeat.py
camfi.egg-info/PKG-INFO
camfi.egg-info/SOURCES.txt
camfi.egg-info/dependency_links.txt
camfi.egg-info/entry_points.txt
camfi.egg-info/requires.txt
camfi.egg-info/top_level.txt
camfi/datamodel/__init__.py
camfi/datamodel/_region_filter_config_dynamic.py
camfi/datamodel/autoannotation.py
camfi/datamodel/geometry.py
camfi/datamodel/locationtime.py
camfi/datamodel/region_filter_config.py
camfi/datamodel/via.py
camfi/datamodel/via_region_attributes.py
camfi/datamodel/weather.py
camfi/plotting/__init__.py
camfi/plotting/matplotlib.py