Metadata-Version: 2.1
Name: camfi
Version: 2.1.2
Summary: Camera-based Analysis and Monitoring of Flying Insects
Home-page: https://github.com/J-Wall/camfi
Author: Jesse Wallace
Author-email: jesse.wallace@anu.edu.au
License: UNKNOWN
Keywords: ecology,monitoring,insects,wingbeat frequency
Platform: UNKNOWN
Classifier: Development Status :: 3 - Alpha
Classifier: Intended Audience :: Science/Research
Classifier: Topic :: Scientific/Engineering :: Bio-Informatics
Classifier: Topic :: Scientific/Engineering :: Image Processing
Classifier: License :: OSI Approved :: MIT License
Classifier: Programming Language :: Python :: 3
Classifier: Programming Language :: Python :: 3.9
Classifier: Programming Language :: Python :: 3 :: Only
Requires-Python: >=3.9, <4
